{
  "country": "Argentina",
  "date": "2026-06-24",
  "cities": [
    {
      "country": "Argentina",
      "country_code": "AR",
      "city": "Rosario",
      "latitude": -32.9442,
      "longitude": -60.6505,
      "timestamp": "2026-06-24T11:40:08.955286",
      "current": {
        "time": "2026-06-24T08:30",
        "interval": 900,
        "temperature_2m": 2.9,
        "relative_humidity_2m": 91,
        "apparent_temperature": 0.0,
        "weather_code": 0,
        "wind_speed_10m": 6.7,
        "wind_direction_10m": 272
      },
      "history_24h": null
    },
    {
      "country": "Argentina",
      "country_code": "AR",
      "city": "Bariloche",
      "latitude": -41.1335,
      "longitude": -71.3103,
      "timestamp": "2026-06-24T11:40:08.957118",
      "current": {
        "time": "2026-06-24T08:30",
        "interval": 900,
        "temperature_2m": 4.8,
        "relative_humidity_2m": 92,
        "apparent_temperature": 0.6,
        "weather_code": 3,
        "wind_speed_10m": 18.2,
        "wind_direction_10m": 293
      },
      "history_24h": null
    },
    {
      "country": "Argentina",
      "country_code": "AR",
      "city": "Mendoza",
      "latitude": -32.8895,
      "longitude": -68.8458,
      "timestamp": "2026-06-24T11:40:08.958263",
      "current": {
        "time": "2026-06-24T08:30",
        "interval": 900,
        "temperature_2m": 1.5,
        "relative_humidity_2m": 59,
        "apparent_temperature": -1.9,
        "weather_code": 2,
        "wind_speed_10m": 3.5,
        "wind_direction_10m": 28
      },
      "history_24h": null
    },
    {
      "country": "Argentina",
      "country_code": "AR",
      "city": "Cordoba",
      "latitude": -31.4201,
      "longitude": -64.1888,
      "timestamp": "2026-06-24T11:40:08.961073",
      "current": {
        "time": "2026-06-24T08:30",
        "interval": 900,
        "temperature_2m": 3.1,
        "relative_humidity_2m": 66,
        "apparent_temperature": -0.4,
        "weather_code": 0,
        "wind_speed_10m": 6.3,
        "wind_direction_10m": 353
      },
      "history_24h": null
    },
    {
      "country": "Argentina",
      "country_code": "AR",
      "city": "Buenos Aires",
      "latitude": -34.6037,
      "longitude": -58.3816,
      "timestamp": "2026-06-24T11:40:10.047327",
      "current": {
        "time": "2026-06-24T08:30",
        "interval": 900,
        "temperature_2m": 3.4,
        "relative_humidity_2m": 88,
        "apparent_temperature": 0.3,
        "weather_code": 0,
        "wind_speed_10m": 8.1,
        "wind_direction_10m": 265
      },
      "history_24h": null
    }
  ]
}