{
  "country": "Canada",
  "date": "2026-07-01",
  "cities": [
    {
      "country": "Canada",
      "country_code": "CA",
      "city": "Toronto",
      "latitude": 43.6532,
      "longitude": -79.3832,
      "timestamp": "2026-07-01T11:54:05.747271",
      "current": {
        "time": "2026-07-01T07:45",
        "interval": 900,
        "temperature_2m": 24.2,
        "relative_humidity_2m": 90,
        "apparent_temperature": 29.0,
        "weather_code": 0,
        "wind_speed_10m": 2.6,
        "wind_direction_10m": 56
      },
      "history_24h": null
    },
    {
      "country": "Canada",
      "country_code": "CA",
      "city": "Vancouver",
      "latitude": 49.2827,
      "longitude": -123.1207,
      "timestamp": "2026-07-01T11:54:05.748664",
      "current": {
        "time": "2026-07-01T04:45",
        "interval": 900,
        "temperature_2m": 12.7,
        "relative_humidity_2m": 86,
        "apparent_temperature": 11.9,
        "weather_code": 1,
        "wind_speed_10m": 6.5,
        "wind_direction_10m": 124
      },
      "history_24h": null
    },
    {
      "country": "Canada",
      "country_code": "CA",
      "city": "Montreal",
      "latitude": 45.5017,
      "longitude": -73.5673,
      "timestamp": "2026-07-01T11:54:05.751902",
      "current": {
        "time": "2026-07-01T07:45",
        "interval": 900,
        "temperature_2m": 23.5,
        "relative_humidity_2m": 88,
        "apparent_temperature": 26.4,
        "weather_code": 1,
        "wind_speed_10m": 12.1,
        "wind_direction_10m": 217
      },
      "history_24h": null
    },
    {
      "country": "Canada",
      "country_code": "CA",
      "city": "Calgary",
      "latitude": 51.0447,
      "longitude": -114.0719,
      "timestamp": "2026-07-01T11:54:05.761223",
      "current": {
        "time": "2026-07-01T05:45",
        "interval": 900,
        "temperature_2m": 11.8,
        "relative_humidity_2m": 89,
        "apparent_temperature": 10.9,
        "weather_code": 0,
        "wind_speed_10m": 6.5,
        "wind_direction_10m": 304
      },
      "history_24h": null
    },
    {
      "country": "Canada",
      "country_code": "CA",
      "city": "Ottawa",
      "latitude": 45.4215,
      "longitude": -75.6972,
      "timestamp": "2026-07-01T11:54:05.763525",
      "current": {
        "time": "2026-07-01T07:45",
        "interval": 900,
        "temperature_2m": 22.6,
        "relative_humidity_2m": 93,
        "apparent_temperature": 26.0,
        "weather_code": 0,
        "wind_speed_10m": 7.9,
        "wind_direction_10m": 204
      },
      "history_24h": null
    }
  ]
}