{
  "country": "Denmark",
  "date": "2026-05-19",
  "cities": [
    {
      "country": "Denmark",
      "country_code": "DK",
      "city": "Copenhagen",
      "latitude": 55.6761,
      "longitude": 12.5683,
      "timestamp": "2026-05-19T17:43:07.757171",
      "current": {
        "time": "2026-05-19T19:30",
        "interval": 900,
        "temperature_2m": 16.5,
        "relative_humidity_2m": 50,
        "apparent_temperature": 14.1,
        "weather_code": 0,
        "wind_speed_10m": 9.4,
        "wind_direction_10m": 181
      },
      "history_24h": null
    },
    {
      "country": "Denmark",
      "country_code": "DK",
      "city": "Aarhus",
      "latitude": 56.1629,
      "longitude": 10.2039,
      "timestamp": "2026-05-19T17:43:07.759158",
      "current": {
        "time": "2026-05-19T19:30",
        "interval": 900,
        "temperature_2m": 15.4,
        "relative_humidity_2m": 69,
        "apparent_temperature": 13.6,
        "weather_code": 2,
        "wind_speed_10m": 12.2,
        "wind_direction_10m": 152
      },
      "history_24h": null
    },
    {
      "country": "Denmark",
      "country_code": "DK",
      "city": "Odense",
      "latitude": 55.4038,
      "longitude": 10.4027,
      "timestamp": "2026-05-19T17:43:07.762453",
      "current": {
        "time": "2026-05-19T19:30",
        "interval": 900,
        "temperature_2m": 17.6,
        "relative_humidity_2m": 43,
        "apparent_temperature": 14.8,
        "weather_code": 1,
        "wind_speed_10m": 11.2,
        "wind_direction_10m": 184
      },
      "history_24h": null
    },
    {
      "country": "Denmark",
      "country_code": "DK",
      "city": "Aalborg",
      "latitude": 57.0488,
      "longitude": 9.9217,
      "timestamp": "2026-05-19T17:43:07.782847",
      "current": {
        "time": "2026-05-19T19:30",
        "interval": 900,
        "temperature_2m": 17.4,
        "relative_humidity_2m": 59,
        "apparent_temperature": 15.1,
        "weather_code": 1,
        "wind_speed_10m": 14.4,
        "wind_direction_10m": 127
      },
      "history_24h": null
    },
    {
      "country": "Denmark",
      "country_code": "DK",
      "city": "Billund",
      "latitude": 55.7304,
      "longitude": 9.1103,
      "timestamp": "2026-05-19T17:43:07.798006",
      "current": {
        "time": "2026-05-19T19:30",
        "interval": 900,
        "temperature_2m": 17.1,
        "relative_humidity_2m": 80,
        "apparent_temperature": 17.0,
        "weather_code": 1,
        "wind_speed_10m": 8.3,
        "wind_direction_10m": 135
      },
      "history_24h": null
    }
  ]
}