{
  "country": "Italy",
  "date": "2026-06-13",
  "cities": [
    {
      "country": "Italy",
      "country_code": "IT",
      "city": "Rome",
      "latitude": 41.9028,
      "longitude": 12.4964,
      "timestamp": "2026-06-13T15:20:18.640471",
      "current": {
        "time": "2026-06-13T17:15",
        "interval": 900,
        "temperature_2m": 29.3,
        "relative_humidity_2m": 33,
        "apparent_temperature": 27.6,
        "weather_code": 0,
        "wind_speed_10m": 15.2,
        "wind_direction_10m": 266
      },
      "history_24h": null
    },
    {
      "country": "Italy",
      "country_code": "IT",
      "city": "Milan",
      "latitude": 45.4642,
      "longitude": 9.19,
      "timestamp": "2026-06-13T15:20:18.648508",
      "current": {
        "time": "2026-06-13T17:15",
        "interval": 900,
        "temperature_2m": 32.3,
        "relative_humidity_2m": 26,
        "apparent_temperature": 30.9,
        "weather_code": 0,
        "wind_speed_10m": 11.4,
        "wind_direction_10m": 242
      },
      "history_24h": null
    },
    {
      "country": "Italy",
      "country_code": "IT",
      "city": "Naples",
      "latitude": 40.8518,
      "longitude": 14.2681,
      "timestamp": "2026-06-13T15:20:18.650112",
      "current": {
        "time": "2026-06-13T17:15",
        "interval": 900,
        "temperature_2m": 28.2,
        "relative_humidity_2m": 31,
        "apparent_temperature": 25.9,
        "weather_code": 0,
        "wind_speed_10m": 15.3,
        "wind_direction_10m": 278
      },
      "history_24h": null
    },
    {
      "country": "Italy",
      "country_code": "IT",
      "city": "Florence",
      "latitude": 43.7696,
      "longitude": 11.2558,
      "timestamp": "2026-06-13T15:20:18.652304",
      "current": {
        "time": "2026-06-13T17:15",
        "interval": 900,
        "temperature_2m": 30.6,
        "relative_humidity_2m": 33,
        "apparent_temperature": 29.3,
        "weather_code": 0,
        "wind_speed_10m": 14.6,
        "wind_direction_10m": 261
      },
      "history_24h": null
    },
    {
      "country": "Italy",
      "country_code": "IT",
      "city": "Venice",
      "latitude": 45.4408,
      "longitude": 12.3155,
      "timestamp": "2026-06-13T15:20:18.654171",
      "current": {
        "time": "2026-06-13T17:15",
        "interval": 900,
        "temperature_2m": 24.3,
        "relative_humidity_2m": 66,
        "apparent_temperature": 24.8,
        "weather_code": 0,
        "wind_speed_10m": 15.5,
        "wind_direction_10m": 138
      },
      "history_24h": null
    }
  ]
}