{
  "country": "Japan",
  "date": "2026-06-01",
  "cities": [
    {
      "country": "Japan",
      "country_code": "JP",
      "city": "Tokyo",
      "latitude": 35.6762,
      "longitude": 139.6503,
      "timestamp": "2026-06-01T21:49:53.894518",
      "current": {
        "time": "2026-06-02T06:45",
        "interval": 900,
        "temperature_2m": 19.6,
        "relative_humidity_2m": 80,
        "apparent_temperature": 21.2,
        "weather_code": 2,
        "wind_speed_10m": 3.6,
        "wind_direction_10m": 186
      },
      "history_24h": null
    },
    {
      "country": "Japan",
      "country_code": "JP",
      "city": "Kyoto",
      "latitude": 35.0116,
      "longitude": 135.7681,
      "timestamp": "2026-06-01T21:49:53.896816",
      "current": {
        "time": "2026-06-02T06:45",
        "interval": 900,
        "temperature_2m": 19.2,
        "relative_humidity_2m": 96,
        "apparent_temperature": 22.0,
        "weather_code": 65,
        "wind_speed_10m": 2.4,
        "wind_direction_10m": 27
      },
      "history_24h": null
    },
    {
      "country": "Japan",
      "country_code": "JP",
      "city": "Osaka",
      "latitude": 34.6937,
      "longitude": 135.5023,
      "timestamp": "2026-06-01T21:49:53.898369",
      "current": {
        "time": "2026-06-02T06:45",
        "interval": 900,
        "temperature_2m": 19.3,
        "relative_humidity_2m": 96,
        "apparent_temperature": 21.8,
        "weather_code": 63,
        "wind_speed_10m": 5.1,
        "wind_direction_10m": 51
      },
      "history_24h": null
    },
    {
      "country": "Japan",
      "country_code": "JP",
      "city": "Nagoya",
      "latitude": 35.1815,
      "longitude": 136.9066,
      "timestamp": "2026-06-01T21:49:53.900656",
      "current": {
        "time": "2026-06-02T06:45",
        "interval": 900,
        "temperature_2m": 18.4,
        "relative_humidity_2m": 93,
        "apparent_temperature": 20.8,
        "weather_code": 55,
        "wind_speed_10m": 1.1,
        "wind_direction_10m": 342
      },
      "history_24h": null
    },
    {
      "country": "Japan",
      "country_code": "JP",
      "city": "Sapporo",
      "latitude": 43.0618,
      "longitude": 141.3545,
      "timestamp": "2026-06-01T21:49:53.901914",
      "current": {
        "time": "2026-06-02T06:45",
        "interval": 900,
        "temperature_2m": 18.7,
        "relative_humidity_2m": 64,
        "apparent_temperature": 17.3,
        "weather_code": 0,
        "wind_speed_10m": 12.9,
        "wind_direction_10m": 120
      },
      "history_24h": null
    },
    {
      "country": "Japan",
      "country_code": "JP",
      "city": "Yokohama",
      "latitude": 35.4437,
      "longitude": 139.638,
      "timestamp": "2026-06-01T21:49:53.903202",
      "current": {
        "time": "2026-06-02T06:45",
        "interval": 900,
        "temperature_2m": 21.3,
        "relative_humidity_2m": 77,
        "apparent_temperature": 22.7,
        "weather_code": 1,
        "wind_speed_10m": 7.7,
        "wind_direction_10m": 191
      },
      "history_24h": null
    }
  ]
}