{
  "country": "Philippines",
  "date": "2026-07-21",
  "cities": [
    {
      "country": "Philippines",
      "country_code": "PH",
      "city": "Manila",
      "latitude": 14.5995,
      "longitude": 120.9842,
      "timestamp": "2026-07-21T10:58:51.906681",
      "current": {
        "time": "2026-07-21T18:45",
        "interval": 900,
        "temperature_2m": 29.0,
        "relative_humidity_2m": 73,
        "apparent_temperature": 34.4,
        "weather_code": 3,
        "wind_speed_10m": 3.4,
        "wind_direction_10m": 357
      },
      "history_24h": null
    },
    {
      "country": "Philippines",
      "country_code": "PH",
      "city": "Cebu",
      "latitude": 10.3157,
      "longitude": 123.8854,
      "timestamp": "2026-07-21T10:58:51.911419",
      "current": {
        "time": "2026-07-21T18:45",
        "interval": 900,
        "temperature_2m": 25.9,
        "relative_humidity_2m": 97,
        "apparent_temperature": 32.4,
        "weather_code": 3,
        "wind_speed_10m": 3.4,
        "wind_direction_10m": 264
      },
      "history_24h": null
    },
    {
      "country": "Philippines",
      "country_code": "PH",
      "city": "Davao",
      "latitude": 7.0731,
      "longitude": 125.6128,
      "timestamp": "2026-07-21T10:58:51.928810",
      "current": {
        "time": "2026-07-21T18:45",
        "interval": 900,
        "temperature_2m": 25.3,
        "relative_humidity_2m": 90,
        "apparent_temperature": 30.0,
        "weather_code": 3,
        "wind_speed_10m": 8.1,
        "wind_direction_10m": 359
      },
      "history_24h": null
    },
    {
      "country": "Philippines",
      "country_code": "PH",
      "city": "Palawan",
      "latitude": 9.8348,
      "longitude": 118.7383,
      "timestamp": "2026-07-21T10:58:51.944070",
      "current": {
        "time": "2026-07-21T18:45",
        "interval": 900,
        "temperature_2m": 25.7,
        "relative_humidity_2m": 97,
        "apparent_temperature": 32.0,
        "weather_code": 3,
        "wind_speed_10m": 3.9,
        "wind_direction_10m": 304
      },
      "history_24h": null
    },
    {
      "country": "Philippines",
      "country_code": "PH",
      "city": "Boracay",
      "latitude": 11.9674,
      "longitude": 121.924,
      "timestamp": "2026-07-21T10:58:51.945659",
      "current": {
        "time": "2026-07-21T18:45",
        "interval": 900,
        "temperature_2m": 26.9,
        "relative_humidity_2m": 83,
        "apparent_temperature": 30.6,
        "weather_code": 2,
        "wind_speed_10m": 15.2,
        "wind_direction_10m": 246
      },
      "history_24h": null
    }
  ]
}