{
  "country": "Poland",
  "date": "2026-05-26",
  "cities": [
    {
      "country": "Poland",
      "country_code": "PL",
      "city": "Warsaw",
      "latitude": 52.2297,
      "longitude": 21.0122,
      "timestamp": "2026-05-26T18:13:14.506399",
      "current": {
        "time": "2026-05-26T20:00",
        "interval": 900,
        "temperature_2m": 25.3,
        "relative_humidity_2m": 43,
        "apparent_temperature": 23.1,
        "weather_code": 0,
        "wind_speed_10m": 19.1,
        "wind_direction_10m": 295
      },
      "history_24h": null
    },
    {
      "country": "Poland",
      "country_code": "PL",
      "city": "Krakow",
      "latitude": 50.0647,
      "longitude": 19.945,
      "timestamp": "2026-05-26T18:13:14.548256",
      "current": {
        "time": "2026-05-26T20:00",
        "interval": 900,
        "temperature_2m": 25.3,
        "relative_humidity_2m": 43,
        "apparent_temperature": 24.1,
        "weather_code": 0,
        "wind_speed_10m": 12.2,
        "wind_direction_10m": 285
      },
      "history_24h": null
    },
    {
      "country": "Poland",
      "country_code": "PL",
      "city": "Gdansk",
      "latitude": 54.352,
      "longitude": 18.6466,
      "timestamp": "2026-05-26T18:13:14.550027",
      "current": {
        "time": "2026-05-26T20:00",
        "interval": 900,
        "temperature_2m": 20.6,
        "relative_humidity_2m": 41,
        "apparent_temperature": 17.6,
        "weather_code": 2,
        "wind_speed_10m": 15.2,
        "wind_direction_10m": 277
      },
      "history_24h": null
    },
    {
      "country": "Poland",
      "country_code": "PL",
      "city": "Wroclaw",
      "latitude": 51.1079,
      "longitude": 17.0385,
      "timestamp": "2026-05-26T18:13:14.576828",
      "current": {
        "time": "2026-05-26T20:00",
        "interval": 900,
        "temperature_2m": 27.3,
        "relative_humidity_2m": 35,
        "apparent_temperature": 25.7,
        "weather_code": 0,
        "wind_speed_10m": 11.4,
        "wind_direction_10m": 288
      },
      "history_24h": null
    },
    {
      "country": "Poland",
      "country_code": "PL",
      "city": "Poznan",
      "latitude": 52.4064,
      "longitude": 16.9252,
      "timestamp": "2026-05-26T18:13:14.590770",
      "current": {
        "time": "2026-05-26T20:00",
        "interval": 900,
        "temperature_2m": 27.2,
        "relative_humidity_2m": 37,
        "apparent_temperature": 25.5,
        "weather_code": 0,
        "wind_speed_10m": 14.0,
        "wind_direction_10m": 269
      },
      "history_24h": null
    }
  ]
}