{
  "country": "Saudi Arabia",
  "date": "2026-05-22",
  "cities": [
    {
      "country": "Saudi Arabia",
      "country_code": "SA",
      "city": "Riyadh",
      "latitude": 24.7136,
      "longitude": 46.6753,
      "timestamp": "2026-05-22T16:59:33.920175",
      "current": {
        "time": "2026-05-22T19:45",
        "interval": 900,
        "temperature_2m": 34.5,
        "relative_humidity_2m": 12,
        "apparent_temperature": 30.7,
        "weather_code": 0,
        "wind_speed_10m": 12.1,
        "wind_direction_10m": 58
      },
      "history_24h": null
    },
    {
      "country": "Saudi Arabia",
      "country_code": "SA",
      "city": "Jeddah",
      "latitude": 21.4858,
      "longitude": 39.1925,
      "timestamp": "2026-05-22T16:59:33.925641",
      "current": {
        "time": "2026-05-22T19:45",
        "interval": 900,
        "temperature_2m": 30.5,
        "relative_humidity_2m": 50,
        "apparent_temperature": 31.9,
        "weather_code": 0,
        "wind_speed_10m": 13.9,
        "wind_direction_10m": 340
      },
      "history_24h": null
    },
    {
      "country": "Saudi Arabia",
      "country_code": "SA",
      "city": "Mecca",
      "latitude": 21.3891,
      "longitude": 39.8579,
      "timestamp": "2026-05-22T16:59:33.930289",
      "current": {
        "time": "2026-05-22T19:45",
        "interval": 900,
        "temperature_2m": 34.5,
        "relative_humidity_2m": 19,
        "apparent_temperature": 31.9,
        "weather_code": 0,
        "wind_speed_10m": 13.2,
        "wind_direction_10m": 355
      },
      "history_24h": null
    },
    {
      "country": "Saudi Arabia",
      "country_code": "SA",
      "city": "Medina",
      "latitude": 24.5247,
      "longitude": 39.5692,
      "timestamp": "2026-05-22T16:59:33.931842",
      "current": {
        "time": "2026-05-22T19:45",
        "interval": 900,
        "temperature_2m": 36.0,
        "relative_humidity_2m": 12,
        "apparent_temperature": 32.1,
        "weather_code": 0,
        "wind_speed_10m": 13.8,
        "wind_direction_10m": 233
      },
      "history_24h": null
    },
    {
      "country": "Saudi Arabia",
      "country_code": "SA",
      "city": "Dammam",
      "latitude": 26.4207,
      "longitude": 50.0888,
      "timestamp": "2026-05-22T16:59:33.933047",
      "current": {
        "time": "2026-05-22T19:45",
        "interval": 900,
        "temperature_2m": 28.3,
        "relative_humidity_2m": 43,
        "apparent_temperature": 27.9,
        "weather_code": 0,
        "wind_speed_10m": 12.6,
        "wind_direction_10m": 336
      },
      "history_24h": null
    }
  ]
}