{
  "country": "Spain",
  "date": "2026-06-26",
  "cities": [
    {
      "country": "Spain",
      "country_code": "ES",
      "city": "Madrid",
      "latitude": 40.4168,
      "longitude": -3.7038,
      "timestamp": "2026-06-26T11:40:12.342064",
      "current": {
        "time": "2026-06-26T13:30",
        "interval": 900,
        "temperature_2m": 28.8,
        "relative_humidity_2m": 33,
        "apparent_temperature": 30.6,
        "weather_code": 1,
        "wind_speed_10m": 7.0,
        "wind_direction_10m": 215
      },
      "history_24h": null
    },
    {
      "country": "Spain",
      "country_code": "ES",
      "city": "Barcelona",
      "latitude": 41.3851,
      "longitude": 2.1734,
      "timestamp": "2026-06-26T11:40:12.344831",
      "current": {
        "time": "2026-06-26T13:30",
        "interval": 900,
        "temperature_2m": 31.9,
        "relative_humidity_2m": 34,
        "apparent_temperature": 33.6,
        "weather_code": 0,
        "wind_speed_10m": 12.1,
        "wind_direction_10m": 190
      },
      "history_24h": null
    },
    {
      "country": "Spain",
      "country_code": "ES",
      "city": "Valencia",
      "latitude": 39.4699,
      "longitude": -0.3763,
      "timestamp": "2026-06-26T11:40:12.352212",
      "current": {
        "time": "2026-06-26T13:30",
        "interval": 900,
        "temperature_2m": 29.4,
        "relative_humidity_2m": 59,
        "apparent_temperature": 33.4,
        "weather_code": 1,
        "wind_speed_10m": 13.7,
        "wind_direction_10m": 90
      },
      "history_24h": null
    },
    {
      "country": "Spain",
      "country_code": "ES",
      "city": "Seville",
      "latitude": 37.3891,
      "longitude": -5.9845,
      "timestamp": "2026-06-26T11:40:12.353824",
      "current": {
        "time": "2026-06-26T13:30",
        "interval": 900,
        "temperature_2m": 28.7,
        "relative_humidity_2m": 47,
        "apparent_temperature": 32.8,
        "weather_code": 1,
        "wind_speed_10m": 3.9,
        "wind_direction_10m": 248
      },
      "history_24h": null
    },
    {
      "country": "Spain",
      "country_code": "ES",
      "city": "Bilbao",
      "latitude": 43.263,
      "longitude": -2.935,
      "timestamp": "2026-06-26T11:40:12.366534",
      "current": {
        "time": "2026-06-26T13:30",
        "interval": 900,
        "temperature_2m": 32.6,
        "relative_humidity_2m": 34,
        "apparent_temperature": 34.1,
        "weather_code": 0,
        "wind_speed_10m": 6.4,
        "wind_direction_10m": 43
      },
      "history_24h": null
    }
  ]
}