{
  "country": "Turkey",
  "date": "2026-06-21",
  "cities": [
    {
      "country": "Turkey",
      "country_code": "TR",
      "city": "Istanbul",
      "latitude": 41.0082,
      "longitude": 28.9784,
      "timestamp": "2026-06-21T11:39:44.945320",
      "current": {
        "time": "2026-06-21T14:30",
        "interval": 900,
        "temperature_2m": 28.5,
        "relative_humidity_2m": 38,
        "apparent_temperature": 27.9,
        "weather_code": 0,
        "wind_speed_10m": 21.6,
        "wind_direction_10m": 30
      },
      "history_24h": null
    },
    {
      "country": "Turkey",
      "country_code": "TR",
      "city": "Ankara",
      "latitude": 39.9334,
      "longitude": 32.8597,
      "timestamp": "2026-06-21T11:39:44.952708",
      "current": {
        "time": "2026-06-21T14:30",
        "interval": 900,
        "temperature_2m": 25.5,
        "relative_humidity_2m": 29,
        "apparent_temperature": 24.5,
        "weather_code": 1,
        "wind_speed_10m": 13.9,
        "wind_direction_10m": 37
      },
      "history_24h": null
    },
    {
      "country": "Turkey",
      "country_code": "TR",
      "city": "Izmir",
      "latitude": 38.4237,
      "longitude": 27.1428,
      "timestamp": "2026-06-21T11:39:44.955132",
      "current": {
        "time": "2026-06-21T14:30",
        "interval": 900,
        "temperature_2m": 33.4,
        "relative_humidity_2m": 27,
        "apparent_temperature": 33.7,
        "weather_code": 2,
        "wind_speed_10m": 14.8,
        "wind_direction_10m": 39
      },
      "history_24h": null
    },
    {
      "country": "Turkey",
      "country_code": "TR",
      "city": "Antalya",
      "latitude": 36.8969,
      "longitude": 30.7133,
      "timestamp": "2026-06-21T11:39:44.962780",
      "current": {
        "time": "2026-06-21T14:30",
        "interval": 900,
        "temperature_2m": 33.2,
        "relative_humidity_2m": 30,
        "apparent_temperature": 33.9,
        "weather_code": 2,
        "wind_speed_10m": 13.4,
        "wind_direction_10m": 175
      },
      "history_24h": null
    },
    {
      "country": "Turkey",
      "country_code": "TR",
      "city": "Cappadocia",
      "latitude": 38.6431,
      "longitude": 34.8289,
      "timestamp": "2026-06-21T11:39:45.032898",
      "current": {
        "time": "2026-06-21T14:30",
        "interval": 900,
        "temperature_2m": 23.6,
        "relative_humidity_2m": 45,
        "apparent_temperature": 23.9,
        "weather_code": 0,
        "wind_speed_10m": 13.0,
        "wind_direction_10m": 19
      },
      "history_24h": null
    }
  ]
}