{
  "country": "Turkey",
  "date": "2026-06-04",
  "cities": [
    {
      "country": "Turkey",
      "country_code": "TR",
      "city": "Istanbul",
      "latitude": 41.0082,
      "longitude": 28.9784,
      "timestamp": "2026-06-04T17:59:17.408969",
      "current": {
        "time": "2026-06-04T20:45",
        "interval": 900,
        "temperature_2m": 26.2,
        "relative_humidity_2m": 51,
        "apparent_temperature": 26.3,
        "weather_code": 1,
        "wind_speed_10m": 11.2,
        "wind_direction_10m": 6
      },
      "history_24h": null
    },
    {
      "country": "Turkey",
      "country_code": "TR",
      "city": "Ankara",
      "latitude": 39.9334,
      "longitude": 32.8597,
      "timestamp": "2026-06-04T17:59:17.411337",
      "current": {
        "time": "2026-06-04T20:45",
        "interval": 900,
        "temperature_2m": 22.9,
        "relative_humidity_2m": 42,
        "apparent_temperature": 22.5,
        "weather_code": 1,
        "wind_speed_10m": 1.5,
        "wind_direction_10m": 76
      },
      "history_24h": null
    },
    {
      "country": "Turkey",
      "country_code": "TR",
      "city": "Izmir",
      "latitude": 38.4237,
      "longitude": 27.1428,
      "timestamp": "2026-06-04T17:59:17.418764",
      "current": {
        "time": "2026-06-04T20:45",
        "interval": 900,
        "temperature_2m": 24.2,
        "relative_humidity_2m": 56,
        "apparent_temperature": 24.3,
        "weather_code": 2,
        "wind_speed_10m": 10.9,
        "wind_direction_10m": 172
      },
      "history_24h": null
    },
    {
      "country": "Turkey",
      "country_code": "TR",
      "city": "Antalya",
      "latitude": 36.8969,
      "longitude": 30.7133,
      "timestamp": "2026-06-04T17:59:17.419936",
      "current": {
        "time": "2026-06-04T20:45",
        "interval": 900,
        "temperature_2m": 22.6,
        "relative_humidity_2m": 78,
        "apparent_temperature": 24.9,
        "weather_code": 2,
        "wind_speed_10m": 6.0,
        "wind_direction_10m": 73
      },
      "history_24h": null
    },
    {
      "country": "Turkey",
      "country_code": "TR",
      "city": "Cappadocia",
      "latitude": 38.6431,
      "longitude": 34.8289,
      "timestamp": "2026-06-04T17:59:17.420950",
      "current": {
        "time": "2026-06-04T20:45",
        "interval": 900,
        "temperature_2m": 19.9,
        "relative_humidity_2m": 64,
        "apparent_temperature": 20.3,
        "weather_code": 1,
        "wind_speed_10m": 3.7,
        "wind_direction_10m": 151
      },
      "history_24h": null
    }
  ]
}