{
  "country": "Ukraine",
  "date": "2026-07-23",
  "cities": [
    {
      "country": "Ukraine",
      "country_code": "UA",
      "city": "Kyiv",
      "latitude": 50.4501,
      "longitude": 30.5234,
      "timestamp": "2026-07-23T11:02:13.886233",
      "current": {
        "time": "2026-07-23T14:00",
        "interval": 900,
        "temperature_2m": 22.2,
        "relative_humidity_2m": 39,
        "apparent_temperature": 21.1,
        "weather_code": 2,
        "wind_speed_10m": 7.2,
        "wind_direction_10m": 357
      },
      "history_24h": null
    },
    {
      "country": "Ukraine",
      "country_code": "UA",
      "city": "Lviv",
      "latitude": 49.8397,
      "longitude": 24.0297,
      "timestamp": "2026-07-23T11:02:13.913934",
      "current": {
        "time": "2026-07-23T14:00",
        "interval": 900,
        "temperature_2m": 19.9,
        "relative_humidity_2m": 45,
        "apparent_temperature": 17.6,
        "weather_code": 3,
        "wind_speed_10m": 11.2,
        "wind_direction_10m": 250
      },
      "history_24h": null
    },
    {
      "country": "Ukraine",
      "country_code": "UA",
      "city": "Odessa",
      "latitude": 46.4825,
      "longitude": 30.7233,
      "timestamp": "2026-07-23T11:02:13.917061",
      "current": {
        "time": "2026-07-23T14:00",
        "interval": 900,
        "temperature_2m": 19.1,
        "relative_humidity_2m": 73,
        "apparent_temperature": 18.2,
        "weather_code": 3,
        "wind_speed_10m": 16.0,
        "wind_direction_10m": 352
      },
      "history_24h": null
    },
    {
      "country": "Ukraine",
      "country_code": "UA",
      "city": "Kharkiv",
      "latitude": 49.9935,
      "longitude": 36.2304,
      "timestamp": "2026-07-23T11:02:13.923883",
      "current": {
        "time": "2026-07-23T14:00",
        "interval": 900,
        "temperature_2m": 24.5,
        "relative_humidity_2m": 36,
        "apparent_temperature": 23.8,
        "weather_code": 3,
        "wind_speed_10m": 6.1,
        "wind_direction_10m": 315
      },
      "history_24h": null
    },
    {
      "country": "Ukraine",
      "country_code": "UA",
      "city": "Chernivtsi",
      "latitude": 48.2921,
      "longitude": 25.9398,
      "timestamp": "2026-07-23T11:02:13.925018",
      "current": {
        "time": "2026-07-23T14:00",
        "interval": 900,
        "temperature_2m": 22.6,
        "relative_humidity_2m": 35,
        "apparent_temperature": 21.9,
        "weather_code": 3,
        "wind_speed_10m": 5.3,
        "wind_direction_10m": 298
      },
      "history_24h": null
    }
  ]
}