{
  "country": "Vietnam",
  "date": "2026-06-20",
  "cities": [
    {
      "country": "Vietnam",
      "country_code": "VN",
      "city": "Ho Chi Minh City",
      "latitude": 10.8231,
      "longitude": 106.6297,
      "timestamp": "2026-06-20T11:09:54.290495",
      "current": {
        "time": "2026-06-20T18:00",
        "interval": 900,
        "temperature_2m": 27.3,
        "relative_humidity_2m": 86,
        "apparent_temperature": 32.4,
        "weather_code": 51,
        "wind_speed_10m": 10.1,
        "wind_direction_10m": 241
      },
      "history_24h": null
    },
    {
      "country": "Vietnam",
      "country_code": "VN",
      "city": "Hanoi",
      "latitude": 21.0285,
      "longitude": 105.8542,
      "timestamp": "2026-06-20T11:09:54.292726",
      "current": {
        "time": "2026-06-20T18:00",
        "interval": 900,
        "temperature_2m": 32.4,
        "relative_humidity_2m": 75,
        "apparent_temperature": 40.3,
        "weather_code": 3,
        "wind_speed_10m": 3.6,
        "wind_direction_10m": 162
      },
      "history_24h": null
    },
    {
      "country": "Vietnam",
      "country_code": "VN",
      "city": "Da Nang",
      "latitude": 16.0544,
      "longitude": 108.2022,
      "timestamp": "2026-06-20T11:09:54.301599",
      "current": {
        "time": "2026-06-20T18:00",
        "interval": 900,
        "temperature_2m": 30.7,
        "relative_humidity_2m": 71,
        "apparent_temperature": 35.5,
        "weather_code": 0,
        "wind_speed_10m": 13.1,
        "wind_direction_10m": 128
      },
      "history_24h": null
    },
    {
      "country": "Vietnam",
      "country_code": "VN",
      "city": "Hue",
      "latitude": 16.4637,
      "longitude": 107.5869,
      "timestamp": "2026-06-20T11:09:54.314937",
      "current": {
        "time": "2026-06-20T18:00",
        "interval": 900,
        "temperature_2m": 32.5,
        "relative_humidity_2m": 65,
        "apparent_temperature": 37.3,
        "weather_code": 0,
        "wind_speed_10m": 13.6,
        "wind_direction_10m": 98
      },
      "history_24h": null
    },
    {
      "country": "Vietnam",
      "country_code": "VN",
      "city": "Nha Trang",
      "latitude": 12.2451,
      "longitude": 109.1945,
      "timestamp": "2026-06-20T11:09:54.331447",
      "current": {
        "time": "2026-06-20T18:00",
        "interval": 900,
        "temperature_2m": 29.7,
        "relative_humidity_2m": 73,
        "apparent_temperature": 34.0,
        "weather_code": 0,
        "wind_speed_10m": 13.0,
        "wind_direction_10m": 153
      },
      "history_24h": null
    }
  ]
}